<?xml version="1.0" encoding="UTF-8" ?>
<!DOCTYPE configuration PUBLIC "-//mybatis.org//DTD Config 3.0//EN" "http://mybatis.org/dtd/mybatis-3-config.dtd">
<configuration>

    <settings>
        <setting name="cacheEnabled" value="false"/>
        <setting name="lazyLoadingEnabled" value="true"/>
        <setting name="multipleResultSetsEnabled" value="true"/>
        <setting name="useColumnLabel" value="true"/>
        <setting name="useGeneratedKeys" value="false"/>
        <setting name="autoMappingBehavior" value="PARTIAL"/>
        <setting name="defaultExecutorType" value="SIMPLE"/>
        <setting name="defaultStatementTimeout" value="25"/>
        <setting name="localCacheScope" value="SESSION"/>
    </settings>

    <typeAliases>
        <package name="com.xpay.channel.dao.entity"/>
    </typeAliases>

    <mappers>
        <mapper resource="mybatis/mapper/payInfoMapper.xml"/>
        <mapper resource="mybatis/mapper/channelCfgMapper.xml"/>
        <mapper resource="mybatis/mapper/instMerchantMapper.xml"/>
        <mapper resource="mybatis/mapper/payToolsBankMapper.xml"/>
        <mapper resource="mybatis/mapper/payToolsMappingMapper.xml"/>
    </mappers>
</configuration>